README.rst
setup.py
bin/blirupgameoflife
bin/blirupgameoflife.bat
blirupgameoflife/LifeGame.py
blirupgameoflife/__main__.py
blirupgameoflife.egg-info/PKG-INFO
blirupgameoflife.egg-info/SOURCES.txt
blirupgameoflife.egg-info/dependency_links.txt
blirupgameoflife.egg-info/not-zip-safe
blirupgameoflife.egg-info/requires.txt
blirupgameoflife.egg-info/top_level.txt