Metadata-Version: 1.0
Name: blirupgameoflife
Version: 1.0.6
Summary: Conway's Game of Life implemented with PyGame
Home-page: https://github.com/Blirup/gameoflife.git
Author: Blirup
Author-email: martin.blirup@gmail.com
License: GPL-3.0
Platform: UNKNOWN
